LICENSE
MANIFEST.in
README.rst
setup.py
docs/Makefile
docs/.ipynb_checkpoints/examples-checkpoint.ipynb
fdgrid/__init__.py
fdgrid/_exceptions.py
fdgrid/cdomain.py
fdgrid/domains.py
fdgrid/graphics.py
fdgrid/mesh.py
fdgrid/templates.py
fdgrid/utils.py
fdgrid.egg-info/PKG-INFO
fdgrid.egg-info/SOURCES.txt
fdgrid.egg-info/dependency_links.txt
fdgrid.egg-info/requires.txt
fdgrid.egg-info/top_level.txt